unicourt/__init__.py
unicourt/api_client.py
unicourt/configuration.py
unicourt/exceptions.py
unicourt/model_utils.py
unicourt/rest.py
unicourt/utils.py
unicourt/api/__init__.py
unicourt/api/attorney_analytics_api.py
unicourt/api/authentication_api.py
unicourt/api/callback_api.py
unicourt/api/case_analytics_api.py
unicourt/api/case_docket_api.py
unicourt/api/case_documents_api.py
unicourt/api/case_export_api.py
unicourt/api/case_search_api.py
unicourt/api/case_tracking_api.py
unicourt/api/case_update_api.py
unicourt/api/court_availability_api.py
unicourt/api/court_standards_api.py
unicourt/api/judge_analytics_api.py
unicourt/api/law_firm_analytics_api.py
unicourt/api/pacer_api.py
unicourt/api/pacer_credential_api.py
unicourt/api/party_analytics_api.py
unicourt/api/usage_api.py
unicourt/model/__init__.py
unicourt/model/access_token_id_list_response.py
unicourt/model/access_token_id_response.py
unicourt/model/access_token_request.py
unicourt/model/access_token_response.py
unicourt/model/additional_levels.py
unicourt/model/address.py
unicourt/model/area_of_law.py
unicourt/model/area_of_law_response.py
unicourt/model/associated_norm_attorney.py
unicourt/model/associated_norm_attorney_response.py
unicourt/model/associated_norm_judge.py
unicourt/model/associated_norm_judge_response.py
unicourt/model/associated_norm_law_firm.py
unicourt/model/associated_norm_law_firm_response.py
unicourt/model/associated_norm_party.py
unicourt/model/associated_norm_party_response.py
unicourt/model/associated_so_s_person.py
unicourt/model/attorney.py
unicourt/model/attorney_analytics_api.py
unicourt/model/attorney_law_firm.py
unicourt/model/attorney_representation_type.py
unicourt/model/attorney_representation_type_response.py
unicourt/model/attorney_type.py
unicourt/model/attorney_type_response.py
unicourt/model/attorneys.py
unicourt/model/bar_record.py
unicourt/model/bar_record_preview.py
unicourt/model/bar_source_data.py
unicourt-1.0.dist-info/LICENSE
unicourt-1.0.dist-info/METADATA
unicourt-1.0.dist-info/WHEEL
unicourt-1.0.dist-info/top_level.txt
unicourt-1.0.dist-info/RECORD
