Metadata-Version: 2.1
Name: unicourt
Version: 1.0
Summary: Python bindings for the UniCourt Enterprise APIs
Home-page: https://unicourt.com/
Author: UniCourt
Author-email: support@unicourt.com
License: UNKNOWN
Keywords: UniCourt,UniCourt Python Package,UniCourt Enterprise APIs
Platform: UNKNOWN
Requires-Python: >=3.6
Requires-Dist: python-dateutil
Requires-Dist: urllib3 (>=1.25.3)
